weebtools/__init__.py
weebtools/__main__.py
weebtools/utils.py
weebtools/weebException.py
weebtools/images/__init__.py
weebtools/images/imageDownloader.py
weebtools/images/yande.py
weebtools-0.1.2.dist-info/LICENSE
weebtools-0.1.2.dist-info/METADATA
weebtools-0.1.2.dist-info/WHEEL
weebtools-0.1.2.dist-info/top_level.txt
weebtools-0.1.2.dist-info/RECORD
