Metadata-Version: 2.1
Name: weebtools
Version: 0.1.2
Summary: Tools for weebs
Author-email: Shirogane <shirogane23800@gmail.com>
License: GNU GENERAL PUBLIC LICENSE
Project-URL: Homepage, https://github.com/Shirogane23800/weebtools
Keywords: yande.re
Classifier: Programming Language :: Python :: 3.10
Classifier: License :: OSI Approved :: GNU General Public License v3 (GPLv3)
Classifier: Operating System :: OS Independent
Requires-Python: >=3.10
License-File: LICENSE
Requires-Dist: requests (>=2.27.1)
Requires-Dist: beautifulsoup4 (>=4.11.1)
Requires-Dist: crc32c
Requires-Dist: pywin32 (>=304) ; sys_platform == "win32"
